mkdocstrings_handlers/__init__.py
mkdocstrings_handlers/nim/__init__.py
mkdocstrings_handlers/nim/collector.py
mkdocstrings_handlers/nim/docstring.py
mkdocstrings_handlers/nim/handler.py
mkdocstrings_handlers/nim/extractor/extractor.nim
mkdocstrings_handlers/nim/extractor/nimdocinfo.nim
mkdocstrings_handlers/nim/templates/material/attribute.html.jinja
mkdocstrings_handlers/nim/templates/material/backlinks.html.jinja
mkdocstrings_handlers/nim/templates/material/children.html.jinja
mkdocstrings_handlers/nim/templates/material/class.html.jinja
mkdocstrings_handlers/nim/templates/material/const.html.jinja
mkdocstrings_handlers/nim/templates/material/docstring.html.jinja
mkdocstrings_handlers/nim/templates/material/expression.html.jinja
mkdocstrings_handlers/nim/templates/material/func.html.jinja
mkdocstrings_handlers/nim/templates/material/iterator.html.jinja
mkdocstrings_handlers/nim/templates/material/labels.html.jinja
mkdocstrings_handlers/nim/templates/material/language.html.jinja
mkdocstrings_handlers/nim/templates/material/let.html.jinja
mkdocstrings_handlers/nim/templates/material/macro.html.jinja
mkdocstrings_handlers/nim/templates/material/module.html.jinja
mkdocstrings_handlers/nim/templates/material/proc.html.jinja
mkdocstrings_handlers/nim/templates/material/signature.html.jinja
mkdocstrings_handlers/nim/templates/material/style.css
mkdocstrings_handlers/nim/templates/material/summary.html.jinja
mkdocstrings_handlers/nim/templates/material/template.html.jinja
mkdocstrings_handlers/nim/templates/material/type.html.jinja
mkdocstrings_handlers/nim/templates/material/type_alias.html.jinja
mkdocstrings_handlers/nim/templates/material/type_parameters.html.jinja
mkdocstrings_handlers/nim/templates/material/var.html.jinja
mkdocstrings_handlers/nim/templates/material/_base/attribute.html.jinja
mkdocstrings_handlers/nim/templates/material/_base/backlinks.html.jinja
mkdocstrings_handlers/nim/templates/material/_base/children.html.jinja
mkdocstrings_nim-0.2.1.dist-info/METADATA
mkdocstrings_nim-0.2.1.dist-info/WHEEL
mkdocstrings_nim-0.2.1.dist-info/entry_points.txt
mkdocstrings_nim-0.2.1.dist-info/licenses/LICENSE
mkdocstrings_nim-0.2.1.dist-info/RECORD
