Metadata-Version: 2.4
Name: mkdocstrings-nim
Version: 0.2.1
Summary: A Nim handler for mkdocstrings
Project-URL: Homepage, https://github.com/elijahr/mkdocstrings-nim
Project-URL: Documentation, https://elijahr.github.io/mkdocstrings-nim/
Project-URL: Repository, https://github.com/elijahr/mkdocstrings-nim
Project-URL: Issues, https://github.com/elijahr/mkdocstrings-nim/issues
Project-URL: Changelog, https://github.com/elijahr/mkdocstrings-nim/blob/main/CHANGELOG.md
Author: Elijah Rutschman
License-Expression: MIT
License-File: LICENSE
Keywords: api-docs,documentation,mkdocs,mkdocstrings,nim
Classifier: Development Status :: 3 - Alpha
Classifier: Intended Audience :: Developers
Classifier: License :: OSI Approved :: MIT License
Classifier: Programming Language :: Python :: 3
Classifier: Programming Language :: Python :: 3.9
Classifier: Programming Language :: Python :: 3.10
Classifier: Programming Language :: Python :: 3.11
Classifier: Programming Language :: Python :: 3.12
Classifier: Topic :: Documentation
Classifier: Topic :: Software Development :: Documentation
Classifier: Typing :: Typed
Requires-Python: >=3.9
Requires-Dist: docstring-parser>=0.15
Requires-Dist: jinja2>=3.0
Requires-Dist: markupsafe>=2.0
Requires-Dist: mkdocstrings>=0.20
Requires-Dist: pygments>=2.0
Provides-Extra: dev
Requires-Dist: mypy>=1.13; extra == 'dev'
Requires-Dist: pre-commit>=4.0; extra == 'dev'
Requires-Dist: pytest-asyncio; extra == 'dev'
Requires-Dist: pytest-cov; extra == 'dev'
Requires-Dist: pytest-mock; extra == 'dev'
Requires-Dist: pytest-xdist; extra == 'dev'
Requires-Dist: pytest>=7.0; extra == 'dev'
Requires-Dist: ruff>=0.8; extra == 'dev'
Requires-Dist: types-pygments; extra == 'dev'
Provides-Extra: docs
Requires-Dist: mike>=2.0; extra == 'docs'
Requires-Dist: mkdocs-git-revision-date-localized-plugin>=1.2; extra == 'docs'
Requires-Dist: mkdocs-glightbox>=0.3; extra == 'docs'
Requires-Dist: mkdocs-material>=9.0; extra == 'docs'
Requires-Dist: mkdocs>=1.5; extra == 'docs'
Requires-Dist: pymdown-extensions>=10.0; extra == 'docs'
